CHANGELOG
LICENSE
MANIFEST.in
README.md
__init__.py
setup.cfg
setup.py
test-new-relic-api.py
test.py
test2.py
Congo.egg-info/PKG-INFO
Congo.egg-info/SOURCES.txt
Congo.egg-info/dependency_links.txt
Congo.egg-info/entry_points.txt
Congo.egg-info/not-zip-safe
Congo.egg-info/pbr.json
Congo.egg-info/requires.txt
Congo.egg-info/top_level.txt
devtest/__init__.py
devtest/manage.py
devtest/run_boom.py
devtest/run_hello.py
devtest/run_toto.py
devtest/run_www.py
devtest/application/__init__.py
devtest/application/config.py
devtest/application/model.py
devtest/application/test.py
devtest/application/www/__init__.py
devtest/application/www/views.py
portfolio/__init__.py
portfolio/__init__.pyc
portfolio/cmd.py
portfolio/cmd.pyc
portfolio/pkginfo.py
portfolio/pkginfo.pyc
portfolio/utils.py
portfolio/utils.pyc
portfolio/app-skel/README.txt
portfolio/app-skel/__init__.py
portfolio/app-skel/config.py
portfolio/app-skel/init.py
portfolio/app-skel/manage.py
portfolio/app-skel/model.py
portfolio/app-skel/propel.yml
portfolio/app-skel/run.py
portfolio/app-skel/admin/__init__.py
portfolio/app-skel/admin/views.py
portfolio/app-skel/admin/static/css/style.css
portfolio/app-skel/admin/static/img/blank
portfolio/app-skel/admin/static/js/app.js
portfolio/app-skel/admin/static/vendor/bootstrap/css/bootstrap-theme.css
portfolio/app-skel/admin/static/vendor/bootstrap/css/bootstrap-theme.css.map
portfolio/app-skel/admin/static/vendor/bootstrap/css/bootstrap-theme.min.css
portfolio/app-skel/admin/static/vendor/bootstrap/css/bootstrap.css
portfolio/app-skel/admin/static/vendor/bootstrap/css/bootstrap.css.map
portfolio/app-skel/admin/static/vendor/bootstrap/css/bootstrap.min.css
portfolio/app-skel/admin/static/vendor/bootstrap/fonts/glyphicons-halflings-regular.eot
portfolio/app-skel/admin/static/vendor/bootstrap/fonts/glyphicons-halflings-regular.svg
portfolio/app-skel/admin/static/vendor/bootstrap/fonts/glyphicons-halflings-regular.ttf
portfolio/app-skel/admin/static/vendor/bootstrap/fonts/glyphicons-halflings-regular.woff
portfolio/app-skel/admin/static/vendor/bootstrap/js/bootstrap.js
portfolio/app-skel/admin/static/vendor/bootstrap/js/bootstrap.min.js
portfolio/app-skel/admin/static/vendor/bootswatch/README
